jsonrpc_server/__init__.py
jsonrpc_server/server.py
tests/__init__.py
tests/server_fixture.py
tests/test_server.py
jsonrpc_server_py-0.2.0.dist-info/LICENSE
jsonrpc_server_py-0.2.0.dist-info/METADATA
jsonrpc_server_py-0.2.0.dist-info/WHEEL
jsonrpc_server_py-0.2.0.dist-info/entry_points.txt
jsonrpc_server_py-0.2.0.dist-info/top_level.txt
jsonrpc_server_py-0.2.0.dist-info/RECORD
