Metadata-Version: 2.1
Name: jsonrpc-server-py
Version: 0.2.0
Summary: A simple JSON-RPC server
Home-page: https://github.com/gclluch/jsonrpc-server
Author: Gabriel Lluch
Author-email: gclluch@gmail.com
License: MIT
Project-URL: Documentation, https://github.com/gclluch/jsonrpc-server/blob/main/README.md
Project-URL: Source, https://github.com/gclluch/jsonrpc-server
Project-URL: Tracker, https://github.com/gclluch/jsonrpc-server/issues
Classifier: Programming Language :: Python :: 3
Classifier: License :: OSI Approved :: MIT License
Classifier: Operating System :: OS Independent
Requires-Python: >=3.6
License-File: LICENSE
Requires-Dist: requests
Provides-Extra: dev
Requires-Dist: check-manifest ; extra == 'dev'
Provides-Extra: test
Requires-Dist: coverage ; extra == 'test'
